fjcli/__init__.py
fjcli/__main__.py
fjcli-0.0.0.dist-info/METADATA
fjcli-0.0.0.dist-info/WHEEL
fjcli-0.0.0.dist-info/RECORD
