Metadata-Version: 2.3
Name: fjcli
Version: 0.0.0
Summary: fjcli, print one proverb from https://fun.okdevtv.com/
Project-URL: Homepage, https://github.com/kenu/funjava/
Project-URL: Issues, https://github.com/kenu/funjava/issues
Author-email: David Timber <dxdt@dev.snart.me>
Classifier: License :: OSI Approved :: Apache Software License
Classifier: Operating System :: OS Independent
Classifier: Programming Language :: Python :: 3
Requires-Python: >=3
